soupmatchers/__init__.py
soupmatchers-0.5.dist-info/METADATA
soupmatchers-0.5.dist-info/WHEEL
soupmatchers-0.5.dist-info/top_level.txt
soupmatchers-0.5.dist-info/RECORD
