Metadata-Version: 2.1
Name: soupmatchers
Version: 0.5
Summary: Matchers for checking parts of a HTML parse tree
Home-page: http://launchpad.net/soupmatchers
License: Eclipse Public License
Platform: UNKNOWN
Classifier: Development Status :: 5 - Production/Stable
Classifier: Intended Audience :: Developers
Classifier: License :: OSI Approved :: Eclipse Public License 1.0 (EPL-1.0)
Classifier: Programming Language :: Python
Classifier: Programming Language :: Python :: 2
Classifier: Programming Language :: Python :: 3
Classifier: Topic :: Text Processing :: Markup :: HTML
Classifier: Topic :: Software Development :: Testing
Requires-Dist: testtools (>0.9.3)
Requires-Dist: beautifulsoup4
